odoo/addons/mrp_flattened_bom_xlsx_direct_materials_cost/README.rst
odoo/addons/mrp_flattened_bom_xlsx_direct_materials_cost/__init__.py
odoo/addons/mrp_flattened_bom_xlsx_direct_materials_cost/__manifest__.py
odoo/addons/mrp_flattened_bom_xlsx_direct_materials_cost/i18n/it.po
odoo/addons/mrp_flattened_bom_xlsx_direct_materials_cost/i18n/mrp_flattened_bom_xlsx_direct_materials_cost.pot
odoo/addons/mrp_flattened_bom_xlsx_direct_materials_cost/models/__init__.py
odoo/addons/mrp_flattened_bom_xlsx_direct_materials_cost/models/mrp_bom.py
odoo/addons/mrp_flattened_bom_xlsx_direct_materials_cost/models/product.py
odoo/addons/mrp_flattened_bom_xlsx_direct_materials_cost/readme/CONTRIBUTORS.rst
odoo/addons/mrp_flattened_bom_xlsx_direct_materials_cost/readme/DESCRIPTION.rst
odoo/addons/mrp_flattened_bom_xlsx_direct_materials_cost/readme/USAGE.rst
odoo/addons/mrp_flattened_bom_xlsx_direct_materials_cost/report/__init__.py
odoo/addons/mrp_flattened_bom_xlsx_direct_materials_cost/report/flattened_bom_xlsx.py
odoo/addons/mrp_flattened_bom_xlsx_direct_materials_cost/static/description/icon.png
odoo/addons/mrp_flattened_bom_xlsx_direct_materials_cost/static/description/index.html
odoo13_addon_mrp_flattened_bom_xlsx_direct_materials_cost-13.0.1.0.1.dev5.dist-info/METADATA
odoo13_addon_mrp_flattened_bom_xlsx_direct_materials_cost-13.0.1.0.1.dev5.dist-info/WHEEL
odoo13_addon_mrp_flattened_bom_xlsx_direct_materials_cost-13.0.1.0.1.dev5.dist-info/top_level.txt
odoo13_addon_mrp_flattened_bom_xlsx_direct_materials_cost-13.0.1.0.1.dev5.dist-info/RECORD
